Workbook

Sheet Monthly P&L
A1: TOTALGUARD YARD CARE — 2026 PROFIT & LOSS
A2: Category | B2: January | C2: February | D2: March | E2: April | F2: May | G2: June | H2: July | I2: August | J2: September | K2: October | L2: November | M2: December | N2: YTD Total | O2: % of Revenue
A3: REVENUE
A4: Service Revenue | N4: =SUM(B4:M4) | O4: =IF(N$6=0,0,N4/N$6)
A5: Other Income | N5: =SUM(B5:M5) | O5: =IF(N$6=0,0,N5/N$6)
A6: TOTAL REVENUE | B6: =B4+B5 | C6: =C4+C5 | D6: =D4+D5 | E6: =E4+E5 | F6: =F4+F5 | G6: =G4+G5 | H6: =H4+H5 | I6: =I4+I5 | ... M6: =M4+M5 | N6: =SUM(B6:M6) | O6: =IF(N$6=0,0,N6/N$6)
A8: COST OF GOODS SOLD
A9: Fuel & Gas | N9: =SUM(B9:M9) | O9: =IF(N$6=0,0,N9/N$6)
A10: Supplies & Materials | N10: =SUM(B10:M10) | O10: =IF(N$6=0,0,N10/N$6)
A11: Subcontractor Labor | N11: =SUM(B11:M11) | O11: =IF(N$6=0,0,N11/N$6)
A12: Equipment Rental | N12: =SUM(B12:M12) | O12: =IF(N$6=0,0,N12/N$6)
A13: TOTAL COGS | B13: =B9+B10+B11+B12 | C13: =C9+C10+C11+C12 | D13: =D9+D10+D11+D12 | E13: =E9+E10+E11+E12 | F13: =F9+F10+F11+F12 | G13: =G9+G10+G11+G12 | H13: =H9+H10+H11+H12 | I13: =I9+I10+I11+I12 | ... M13: =M9+M10+M11+M12 | N13: =SUM(B13:M13) | O13: =IF(N$6=0,0,N13/N$6)
A15: GROSS PROFIT | B15: =B6-B13 | C15: =C6-C13 | D15: =D6-D13 | E15: =E6-E13 | F15: =F6-F13 | G15: =G6-G13 | H15: =H6-H13 | I15: =I6-I13 | ... M15: =M6-M13 | N15: =SUM(B15:M15) | O15: =IF(N$6=0,0,N15/N$6)
A16: Gross Margin % | B16: =IF(B6=0,0,B15/B6) | C16: =IF(C6=0,0,C15/C6) | D16: =IF(D6=0,0,D15/D6) | E16: =IF(E6=0,0,E15/E6) | F16: =IF(F6=0,0,F15/F6) | G16: =IF(G6=0,0,G15/G6) | H16: =IF(H6=0,0,H15/H6) | I16: =IF(I6=0,0,I15/I6) | ... N16: =IF(N6=0,0,N15/N6)
A18: OPERATING EXPENSES
A19: Software/SaaS | N19: =SUM(B19:M19) | O19: =IF(N$6=0,0,N19/N$6)
A20: Phone/Communications | N20: =SUM(B20:M20) | O20: =IF(N$6=0,0,N20/N$6)
A21: Insurance | N21: =SUM(B21:M21) | O21: =IF(N$6=0,0,N21/N$6)
A22: Marketing/Advertising | N22: =SUM(B22:M22) | O22: =IF(N$6=0,0,N22/N$6)
A23: Vehicle Expenses | N23: =SUM(B23:M23) | O23: =IF(N$6=0,0,N23/N$6)
A24: Equipment Maintenance | N24: =SUM(B24:M24) | O24: =IF(N$6=0,0,N24/N$6)
A25: Office/Admin | N25: =SUM(B25:M25) | O25: =IF(N$6=0,0,N25/N$6)
A26: Licensing/Permits | N26: =SUM(B26:M26) | O26: =IF(N$6=0,0,N26/N$6)
A27: Training/Education | N27: =SUM(B27:M27) | O27: =IF(N$6=0,0,N27/N$6)
A28: Other Expenses | N28: =SUM(B28:M28) | O28: =IF(N$6=0,0,N28/N$6)
A29: TOTAL OPEX | B29: =B19+B20+B21+B22+B23+B24+B25+B26+B27+B28 | C29: =C19+C20+C21+C22+C23+C24+C25+C26+C27+C28 | D29: =D19+D20+D21+D22+D23+D24+D25+D26+D27+D28 | E29: =E19+E20+E21+E22+E23+E24+E25+E26+E27+E28 | F29: =F19+F20+F21+F22+F23+F24+F25+F26+F27+F28 | G29: =G19+G20+G21+G22+G23+G24+G25+G26+G27+G28 | H29: =H19+H20+H21+H22+H23+H24+H25+H26+H27+H28 | I29: =I19+I20+I21+I22+I23+I24+I25+I26+I27+I28 | ... M29: =M19+M20+M21+M22+M23+M24+M25+M26+M27+M28 | N29: =SUM(B29:M29) | O29: =IF(N$6=0,0,N29/N$6)
A31: NET INCOME | B31: =B15-B29 | C31: =C15-C29 | D31: =D15-D29 | E31: =E15-E29 | F31: =F15-F29 | G31: =G15-G29 | H31: =H15-H29 | I31: =I15-I29 | ... M31: =M15-M29 | N31: =SUM(B31:M31) | O31: =IF(N$6=0,0,N31/N$6)
A32: Net Margin % | B32: =IF(B6=0,0,B31/B6) | C32: =IF(C6=0,0,C31/C6) | D32: =IF(D6=0,0,D31/D6) | E32: =IF(E6=0,0,E31/E6) | F32: =IF(F6=0,0,F31/F6) | G32: =IF(G6=0,0,G31/G6) | H32: =IF(H6=0,0,H31/H6) | I32: =IF(I6=0,0,I31/I6) | ... N32: =IF(N6=0,0,N31/N6)

Sheet Quarterly Summary
A1: TOTALGUARD YARD CARE — 2026 QUARTERLY SUMMARY
A2: Metric | B2: Q1 | C2: Q2 | D2: Q3 | E2: Q4 | F2: Full Year
A3: Revenue | B3: ='Monthly P&L'!B6+'Monthly P&L'!C6+'Monthly P&L'!D6 | C3: ='Monthly P&L'!E6+'Monthly P&L'!F6+'Monthly P&L'!G6 | D3: ='Monthly P&L'!H6+'Monthly P&L'!I6+'Monthly P&L'!J6 | E3: ='Monthly P&L'!K6+'Monthly P&L'!L6+'Monthly P&L'!M6 | F3: =SUM(B3:E3)
A4: COGS | B4: ='Monthly P&L'!B13+'Monthly P&L'!C13+'Monthly P&L'!D13 | C4: ='Monthly P&L'!E13+'Monthly P&L'!F13+'Monthly P&L'!G13 | D4: ='Monthly P&L'!H13+'Monthly P&L'!I13+'Monthly P&L'!J13 | E4: ='Monthly P&L'!K13+'Monthly P&L'!L13+'Monthly P&L'!M13 | F4: =SUM(B4:E4)
A5: Gross Profit | B5: =B3-B4 | C5: =C3-C4 | D5: =D3-D4 | E5: =E3-E4 | F5: =F3-F4
A6: Gross Margin % | B6: =IF(B3=0,0,B5/B3) | C6: =IF(C3=0,0,C5/C3) | D6: =IF(D3=0,0,D5/D3) | E6: =IF(E3=0,0,E5/E3) | F6: =IF(F3=0,0,F5/F3)
A7: Operating Expenses | B7: ='Monthly P&L'!B29+'Monthly P&L'!C29+'Monthly P&L'!D29 | C7: ='Monthly P&L'!E29+'Monthly P&L'!F29+'Monthly P&L'!G29 | D7: ='Monthly P&L'!H29+'Monthly P&L'!I29+'Monthly P&L'!J29 | E7: ='Monthly P&L'!K29+'Monthly P&L'!L29+'Monthly P&L'!M29 | F7: =SUM(B7:E7)
A8: Net Income | B8: =B5-B7 | C8: =C5-C7 | D8: =D5-D7 | E8: =E5-E7 | F8: =F5-F7
A9: Net Margin % | B9: =IF(B3=0,0,B8/B3) | C9: =IF(C3=0,0,C8/C3) | D9: =IF(D3=0,0,D8/D3) | E9: =IF(E3=0,0,E8/E3) | F9: =IF(F3=0,0,F8/F3)
