Workbook

Sheet QUOTE CALCULATOR
A1: TOTALGUARD YARD CARE — FERTILIZER MASTER SHEET
A3: 5-Step Professional Lawn Program | Wisconsin Cool-Season Grasses | SiteOne Products
B5: ENTER PROPERTY SQUARE FOOTAGE: | D5: 10000 | E5: sqft
B6: YOUR MARKUP MULTIPLIER: | D6: 2.5 | E6: (2.0 = double, 2.5 = standard, 3.0 = premium)
B8: STEP | C8: PRODUCT | D8: BAGS NEEDED | E8: MATERIAL COST | F8: YOUR PRICE | G8: PROFIT
B9: Step 1: Pre-Emergent + Fert | C9: LESCO Stonewall 0.43% 19-0-7 | D9: =ROUNDUP($D$5/12500,0) | E9: =D9*28 | F9: =E9*$D$6 | G9: =F9-E9
B10: Step 2: Weed Control + Feed | C10: LESCO 24-0-6 + Trimec Classic | D10: =ROUNDUP($D$5/12000,0) | E10: =D10*27+ROUNDUP($D$5/85000,0)*60 | F10: =E10*$D$6 | G10: =F10-E10
B11: Step 3: Grub Prevention + Fert | C11: LESCO Merit 0.2% 14-0-0 | D11: =ROUNDUP($D$5/14200,0) | E11: =D11*65 | F11: =E11*$D$6 | G11: =F11-E11
B12: Step 4: Fall Recovery | C12: LESCO 24-0-11 50% PolyPlus | D12: =ROUNDUP($D$5/12000,0) | E12: =D12*48+ROUNDUP($D$5/85000,0)*60 | F12: =E12*$D$6 | G12: =F12-E12
B13: Step 5: Winterizer | C13: LESCO 32-0-10 100% NOS Plus SOP | D13: =ROUNDUP($D$5/16000,0) | E13: =D13*63 | F13: =E13*$D$6 | G13: =F13-E13
B14: FULL 5-STEP PROGRAM TOTALS | E14: =SUM(E9:E13) | F14: =SUM(F9:F13) | G14: =SUM(G9:G13)
B16: MATERIAL COST PER VISIT (avg): | E16: =E14/5
B17: YOUR CHARGE PER VISIT (avg): | F17: =F14/5
B19: QUICK REFERENCE — COMMON PROPERTY SIZES
B20: PROPERTY SIZE | C20: TOTAL MATERIAL | D20: YOUR CHARGE | E20: YOUR PROFIT | F20: PROFIT MARGIN
B21: 5,000 sqft | C21: =ROUNDUP(5000/12500,0)*28+ROUNDUP(5000/12000,0)*27+ROUNDUP(5000/85000,0)*60+ROUNDUP(5000/14200,0)*65+ROUNDUP(5000/12000,0)*48+ROUNDUP(5000/85000,0)*60+ROUNDUP(5000/16000,0)*63 | D21: =C21*$D$6 | E21: =D21-C21 | F21: =E21/D21
B22: 8,000 sqft | C22: =ROUNDUP(8000/12500,0)*28+ROUNDUP(8000/12000,0)*27+ROUNDUP(8000/85000,0)*60+ROUNDUP(8000/14200,0)*65+ROUNDUP(8000/12000,0)*48+ROUNDUP(8000/85000,0)*60+ROUNDUP(8000/16000,0)*63 | D22: =C22*$D$6 | E22: =D22-C22 | F22: =E22/D22
B23: 10,000 sqft | C23: =ROUNDUP(10000/12500,0)*28+ROUNDUP(10000/12000,0)*27+ROUNDUP(10000/85000,0)*60+ROUNDUP(10000/14200,0)*65+ROUNDUP(10000/12000,0)*48+ROUNDUP(10000/85000,0)*60+ROUNDUP(10000/16000,0)*63 | D23: =C23*$D$6 | E23: =D23-C23 | F23: =E23/D23
B24: 15,000 sqft | C24: =ROUNDUP(15000/12500,0)*28+ROUNDUP(15000/12000,0)*27+ROUNDUP(15000/85000,0)*60+ROUNDUP(15000/14200,0)*65+ROUNDUP(15000/12000,0)*48+ROUNDUP(15000/85000,0)*60+ROUNDUP(15000/16000,0)*63 | D24: =C24*$D$6 | E24: =D24-C24 | F24: =E24/D24
B25: 20,000 sqft | C25: =ROUNDUP(20000/12500,0)*28+ROUNDUP(20000/12000,0)*27+ROUNDUP(20000/85000,0)*60+ROUNDUP(20000/14200,0)*65+ROUNDUP(20000/12000,0)*48+ROUNDUP(20000/85000,0)*60+ROUNDUP(20000/16000,0)*63 | D25: =C25*$D$6 | E25: =D25-C25 | F25: =E25/D25
B26: 40,000 sqft | C26: =ROUNDUP(40000/12500,0)*28+ROUNDUP(40000/12000,0)*27+ROUNDUP(40000/85000,0)*60+ROUNDUP(40000/14200,0)*65+ROUNDUP(40000/12000,0)*48+ROUNDUP(40000/85000,0)*60+ROUNDUP(40000/16000,0)*63 | D26: =C26*$D$6 | E26: =D26-C26 | F26: =E26/D26
B27: 80,000 sqft | C27: =ROUNDUP(80000/12500,0)*28+ROUNDUP(80000/12000,0)*27+ROUNDUP(80000/85000,0)*60+ROUNDUP(80000/14200,0)*65+ROUNDUP(80000/12000,0)*48+ROUNDUP(80000/85000,0)*60+ROUNDUP(80000/16000,0)*63 | D27: =C27*$D$6 | E27: =D27-C27 | F27: =E27/D27
B29: NOTE: Prices based on SiteOne estimated pricing. Actual costs may vary by branch/volume. Trimec herbicide included in Steps 2 & 4.
B30: TIP: Change the blue input cells (sq footage & markup) to recalculate everything instantly.

Sheet PRODUCT DATABASE
A1: PRODUCT DATABASE — SITEONE LANDSCAPE SUPPLY
A3: All products verified on SiteOne.com | Prices are estimates (login required for exact pricing) | Links are clickable
B5: STEP 1 — EARLY SPRING: Pre-Emergent + Fertilizer (Late April – Early May)
B6: Apply when soil temps reach 55°F consistently
B7: Type | C7: Product Name | D7: SKU | E7: NPK | F7: Bag Size | G7: Coverage | H7: Est. Price | I7: Notes / Why
B8: RECOMMENDED | C8: LESCO Stonewall 0.43% 19-0-7 30% PolyPlus OPTI45 | D8: 702053 | E8: 19-0-7 | F8: 50 lb | G8: 12,500 sqft | H8: $23–$35 | I8: Best value. LESCO house brand = cheapest at SiteOne. 0.43% Prodiamine is strong crabgrass barrier.
B9: ALTERNATIVE | C9: Lebanon Pro Prodiamine 0.38% 18-0-4 25% CRN | D9: 2241024 | E9: 18-0-4 | F9: 50 lb | G9: 12,500 sqft | H9: $38–$45 | I9: Better NPK for spring feeding. Higher price but premium quality.
B10: PREMIUM | C10: LESCO Dimension 0.15% 19-0-0 30% PolyPlus OPTI45 | D10: 702022 | E10: 19-0-0 | F10: 50 lb | G10: 12,500 sqft | H10: $25–$35 | I10: Dimension (Dithiopyr) has early post-emergent activity on young crabgrass that Prodiamine does not.
B12: STEP 2 — LATE SPRING: Weed Control + Feeding (Late May – Early June)
B13: Spray when weeds are actively growing. Spread fertilizer same week.
B14: Type | C14: Product Name | D14: SKU | E14: NPK | F14: Bag Size | G14: Coverage | H14: Est. Price | I14: Notes / Why
B15: RECOMMENDED (Fertilizer) | C15: LESCO 24-0-6 50% PolyPlus OPTI BIO MOP | D15: 511484 | E15: 24-0-6 | F15: 50 lb | G15: 12,000 sqft | H15: $19–$35 | I15: 50% controlled-release nitrogen. Biosolids for organic matter. Great balanced feed.
B16: RECOMMENDED (Herbicide) | C16: Trimec Classic Broadleaf Herbicide — 1 gal | D16: 8811076 | E16: N/A | F16: 1 gallon | G16: ~85,000 sqft | H16: $55–$70 | I16: Industry standard 3-way (2,4-D + Dicamba + MCPP). Controls 90+ broadleaf weeds. 1.5 oz/1,000 sqft rate.
B17: BULK (Herbicide) | C17: Trimec Classic Broadleaf Herbicide — 2.5 gal | D17: 8811126 | E17: N/A | F17: 2.5 gallon | G17: ~213,000 sqft | H17: $130–$170 | I17: Better value for high volume. Same product, bigger jug. Requires pesticide applicator license.
B18: ALTERNATIVE (Herbicide) | C18: Nufarm Triplet SF Herbicide — 2.5 gal | D18: 10447225 | E18: N/A | F18: 2.5 gallon | G18: ~213,000 sqft | H18: $80–$110 | I18: Generic 3-way blend. Cheaper than Trimec, same active ingredients. Good budget option.
B20: STEP 3 — EARLY SUMMER: Grub Prevention + Fertilizer (Late June – Early July)
B21: Apply before grub eggs hatch. Preventative, not curative.
B22: Type | C22: Product Name | D22: SKU | E22: NPK | F22: Bag Size | G22: Coverage | H22: Est. Price | I22: Notes / Why
B23: RECOMMENDED (Combo) | C23: LESCO Merit 0.2% 14-0-0 30% PolyPlus OPTI45 Insecticide + Fert | D23: 291485 | E23: 14-0-0 | F23: 50 lb | G23: 14,200 sqft | H23: $55–$75 | I23: One-pass combo: grub prevention + summer feeding. Merit (Imidacloprid) is the industry standard.
B24: PREMIUM (Combo) | C24: LESCO Acelepryn 0.067% 20-0-5 75% PolyPlus OPTI45 2Fe | D24: 291610 | E24: 20-0-5 | F24: 50 lb | G24: 14,500 sqft | H24: $85–$110 | I24: Premium option. Acelepryn (Chlorantraniliprole) = lower pollinator toxicity, longer residual. Better NPK too.
B25: BUDGET (Separate) | C25: Quali-Pro Imidacloprid 0.5G (grub only) + LESCO 18-0-3 | D25: 83014299 | E25: N/A + 18-0-3 | F25: 30 lb + 50 lb | G25: 16,500 + 14,000 sqft | H25: $30–$45 + $35–$50 | I25: Generic imidacloprid for grubs + separate light summer fert. Two passes but cheapest option.
B27: STEP 4 — LATE SUMMER/EARLY FALL: Lawn Recovery (Late Aug – Early Sep)
B28: Repair summer stress. This is when grass starts growing aggressively again.
B29: Type | C29: Product Name | D29: SKU | E29: NPK | F29: Bag Size | G29: Coverage | H29: Est. Price | I29: Notes / Why
B30: RECOMMENDED | C30: LESCO 24-0-11 50% PolyPlus OPTI 2% Fe 1% Mn MOP | D30: 098631 | E30: 24-0-11 | F30: 50 lb | G30: 12,000 sqft | H30: $40–$55 | I30: Iron + Manganese = dark green color. Potassium builds winter hardiness. The recovery king.
B31: ALTERNATIVE | C31: LESCO 24-0-10 75% PolyPlus OPTI45 Spar-TECH | D31: 511673 | E31: 24-0-10 | F31: 50 lb | G31: 12,000 sqft | H31: $45–$60 | I31: 75% slow-release = feeds longer. Spar-TECH coating technology. Premium option.
B32: HERBICIDE (pair with above) | C32: Trimec Classic — same as Step 2 | D32: 8811076 | E32: N/A | F32: 1 gallon | G32: ~85,000 sqft | H32: $55–$70 | I32: Fall is the BEST time to spray broadleaf weeds in Wisconsin. Weeds are pulling nutrients to roots = herbicide goes deeper.
B34: STEP 5 — LATE FALL: Winterizer (Mid October – Early November)
B35: Last application of the year. Grass is still growing roots even after top growth stops.
B36: Type | C36: Product Name | D36: SKU | E36: NPK | F36: Bag Size | G36: Coverage | H36: Est. Price | I36: Notes / Why
B37: RECOMMENDED | C37: LESCO 32-0-10 100% NOS Plus SOP Mini Granular | D37: 511153 | E37: 32-0-10 | F37: 50 lb | G37: 16,000 sqft | H37: $55–$75 | I37: THE winterizer. NOS Plus stabilized nitrogen maximizes root storage. SOP = chloride-free potassium. Mini granule = best coverage.
B38: ALTERNATIVE | C38: LESCO 32-0-10 75% PolyPlus 2% Fe | D38: 510124 | E38: 32-0-10 | F38: 50 lb | G38: 16,000 sqft | H38: $50–$70 | I38: Same NPK, polymer-coated instead of NOS. 2% Iron for late-season color. Slightly cheaper.
B39: BUDGET | C39: LESCO 30-0-10 25% PolyPlus | D39: 510120 | E39: 30-0-10 | F39: 50 lb | G39: 18,750 sqft | H39: $45–$65 | I39: Covers more area per bag (18,750 sqft). Lower slow-release %. Good budget winterizer.
B42: IMPORTANT NOTES
B43: • All prices are ESTIMATES. SiteOne requires a professional account login for exact pricing. Call your local branch.
B44: • LESCO is SiteOne's house brand — always the best pricing at SiteOne locations.
B45: • Trimec Classic requires a pesticide applicator license to purchase.
B46: • Wisconsin SiteOne locations: Madison, Milwaukee, Green Bay, Appleton, Waukesha, Brookfield.
B47: • Buy by the pallet for best pricing. Typical pro discount is 15-25% below retail.
B48: • Product links are clickable — they go directly to the SiteOne product page.

Sheet PROFIT ANALYSIS
A1: PROFIT ANALYSIS — FERTILIZER PROGRAM
A3: Material cost vs. revenue at different markup levels | Linked to Quote Calculator inputs
B5: MARKUP COMPARISON (based on Quote Calculator sq footage)
C6: Material Cost | D6: 2.0x Markup | E6: 2.5x Markup | F6: 3.0x Markup | G6: 3.5x Markup | H6: 4.0x Markup
B7: Step 1: Pre-Emergent + Fert | C7: ='QUOTE CALCULATOR'!E9 | D7: =C7*2.0 | E7: =C7*2.5 | F7: =C7*3.0 | G7: =C7*3.5 | H7: =C7*4.0
B8: Step 2: Weed Control + Feed | C8: ='QUOTE CALCULATOR'!E10 | D8: =C8*2.0 | E8: =C8*2.5 | F8: =C8*3.0 | G8: =C8*3.5 | H8: =C8*4.0
B9: Step 3: Grub Prevention + Fert | C9: ='QUOTE CALCULATOR'!E11 | D9: =C9*2.0 | E9: =C9*2.5 | F9: =C9*3.0 | G9: =C9*3.5 | H9: =C9*4.0
B10: Step 4: Fall Recovery | C10: ='QUOTE CALCULATOR'!E12 | D10: =C10*2.0 | E10: =C10*2.5 | F10: =C10*3.0 | G10: =C10*3.5 | H10: =C10*4.0
B11: Step 5: Winterizer | C11: ='QUOTE CALCULATOR'!E13 | D11: =C11*2.0 | E11: =C11*2.5 | F11: =C11*3.0 | G11: =C11*3.5 | H11: =C11*4.0
B12: FULL PROGRAM TOTAL | C12: =SUM(C7:C11) | D12: =SUM(D7:D11) | E12: =SUM(E7:E11) | F12: =SUM(F7:F11) | G12: =SUM(G7:G11) | H12: =SUM(H7:H11)
B13: PROFIT | D13: =D12-C12 | E13: =E12-C12 | F13: =F12-C12 | G13: =G12-C12 | H13: =H12-C12
B15: SEASONAL REVENUE PROJECTIONS
B16: NUMBER OF PROGRAM CUSTOMERS: | D16: 25
B18: Per Customer | C18: 25 Customers | D18: 50 Customers | E18: 75 Customers | F18: 100 Customers
B19: Total Revenue (2.5x) | C19: ='QUOTE CALCULATOR'!E14*2.5 | D19: =C19*25 | E19: =C19*50 | F19: =C19*75 | G19: =C19*100
B20: Total Revenue (3.0x) | C20: ='QUOTE CALCULATOR'!E14*3.0 | D20: =C20*25 | E20: =C20*50 | F20: =C20*75 | G20: =C20*100
B21: Total Revenue (3.5x) | C21: ='QUOTE CALCULATOR'!E14*3.5 | D21: =C21*25 | E21: =C21*50 | F21: =C21*75 | G21: =C21*100
B22: Total Material Cost | C22: ='QUOTE CALCULATOR'!E14 | D22: =C22*25 | E22: =C22*50 | F22: =C22*75 | G22: =C22*100
B24: PRO TIPS
B25: • The industry standard markup for lawn fertilization is 2.5x–3.0x material cost.
B26: • Steps 4 & 5 (fall applications) are what actually build thick lawns. Never skip them.
B27: • Upsell aeration + overseeding in September — that's where the real margin is.
B28: • Buy product in bulk at start of season. Pallet pricing saves 15-25% at SiteOne.
B29: • Grub control (Step 3) can be charged as a separate premium add-on instead of included.
B30: • Commercial properties (40K+ sqft) should get volume pricing — lower markup, higher total profit.
